st_ant_menu/__init__.py
st_ant_menu/frontend/build/asset-manifest.json
st_ant_menu/frontend/build/bootstrap.min.css
st_ant_menu/frontend/build/index.html
st_ant_menu/frontend/build/precache-manifest.1e898364dcc134a0feb42243096add8c.js
st_ant_menu/frontend/build/precache-manifest.343bb1a1a8f52006473bf8ee97d48c8d.js
st_ant_menu/frontend/build/precache-manifest.36feaaf18174212fc51881d013cbf19e.js
st_ant_menu/frontend/build/precache-manifest.4df14620fc07390c75978aa22ca98a16.js
st_ant_menu/frontend/build/precache-manifest.a87188cff083f744b28120b7da59fa61.js
st_ant_menu/frontend/build/precache-manifest.b3100fcdda99bc7575018310a5435793.js
st_ant_menu/frontend/build/precache-manifest.b560f9ad796585a743147cb574a1d0c4.js
st_ant_menu/frontend/build/service-worker.js
st_ant_menu/frontend/build/static/js/2.27e192cb.chunk.js
st_ant_menu/frontend/build/static/js/2.27e192cb.chunk.js.LICENSE.txt
st_ant_menu/frontend/build/static/js/2.27e192cb.chunk.js.map
st_ant_menu/frontend/build/static/js/2.9216c681.chunk.js
st_ant_menu/frontend/build/static/js/2.9216c681.chunk.js.LICENSE.txt
st_ant_menu/frontend/build/static/js/2.9216c681.chunk.js.map
st_ant_menu/frontend/build/static/js/main.60d02488.chunk.js
st_ant_menu/frontend/build/static/js/main.60d02488.chunk.js.map
st_ant_menu/frontend/build/static/js/main.61fa3924.chunk.js
st_ant_menu/frontend/build/static/js/main.61fa3924.chunk.js.map
st_ant_menu/frontend/build/static/js/main.6ac583b8.chunk.js
st_ant_menu/frontend/build/static/js/main.6ac583b8.chunk.js.map
st_ant_menu/frontend/build/static/js/main.81977b01.chunk.js
st_ant_menu/frontend/build/static/js/main.81977b01.chunk.js.map
st_ant_menu/frontend/build/static/js/main.aa255291.chunk.js
st_ant_menu/frontend/build/static/js/main.aa255291.chunk.js.map
st_ant_menu/frontend/build/static/js/main.b67ec69f.chunk.js
st_ant_menu/frontend/build/static/js/main.b67ec69f.chunk.js.map
st_ant_menu/frontend/build/static/js/main.fc99ca09.chunk.js
st_ant_menu-0.0.17.dist-info/LICENSE
st_ant_menu-0.0.17.dist-info/METADATA
st_ant_menu-0.0.17.dist-info/WHEEL
st_ant_menu-0.0.17.dist-info/top_level.txt
st_ant_menu-0.0.17.dist-info/RECORD
