Metadata-Version: 2.1
Name: st-ant-menu
Version: 0.0.17
Summary: Streamlit Component for ANT Menu
Home-page: https://github.com/flucas96/st_ant_menu
Author: 
Author-email: 
Requires-Python: >=3.6
License-File: LICENSE
Requires-Dist: streamlit (>=0.63)
